app/__init__.py
app/cli.py
app/config.py
app/emr_client.py
app/emr_job_api.py
app/run_api.py
app/schema.py
emrrunner-1.0.10.dist-info/licenses/LICENSE.md
emrrunner-1.0.10.dist-info/METADATA
emrrunner-1.0.10.dist-info/WHEEL
emrrunner-1.0.10.dist-info/entry_points.txt
emrrunner-1.0.10.dist-info/top_level.txt
emrrunner-1.0.10.dist-info/RECORD
