Metadata-Version: 2.4
Name: emrrunner
Version: 1.0.10
Summary: A powerful command-line tool and API for managing Spark jobs on Amazon EMR clusters
Home-page: https://github.com/Haabiy/EMRRunner
Author: Haabiy
Author-email: Haabiy <abiy.dema@gmail.com>
Maintainer-email: Haabiy <abiy.dema@gmail.com>
License: Permission is hereby granted, free of charge, to any person obtaining a copy of this software and associated documentation files (the "Software"), to deal in the Software without restriction, including without limitation the rights to use, copy, modify, merge, publish, distribute, sublicense, and/or sell copies of the Software, and to permit persons to whom the Software is furnished to do so, subject to the following conditions:
Project-URL: Homepage, https://github.com/Haabiy/EMRRunner
Project-URL: Documentation, https://github.com/Haabiy/EMRRunner#readme
Project-URL: Repository, https://github.com/Haabiy/EMRRunner.git
Project-URL: Issues, https://github.com/Haabiy/EMRRunner/issues
Keywords: emr,aws,spark,data-engineering,cli,emr-runner,spark-jobs
Classifier: Development Status :: 4 - Beta
Classifier: Environment :: Console
Classifier: Intended Audience :: Developers
Classifier: Intended Audience :: System Administrators
Classifier: License :: OSI Approved :: MIT License
Classifier: Operating System :: OS Independent
Classifier: Programming Language :: Python :: 3
Classifier: Programming Language :: Python :: 3.9
Classifier: Topic :: System :: Systems Administration
Classifier: Topic :: Software Development :: Libraries :: Python Modules
Classifier: Framework :: Flask
Requires-Python: >=3.9
License-File: LICENSE.md
Requires-Dist: Flask
Requires-Dist: boto3
Requires-Dist: python-dotenv
Requires-Dist: marshmallow
Requires-Dist: argparse
Dynamic: author
Dynamic: home-page
Dynamic: license-file
Dynamic: requires-python
